LICENSE
README.md
fastapi_gateway_ultra/__init__.py
fastapi_gateway_ultra/core.py
fastapi_gateway_ultra/network.py
fastapi_gateway_ultra/utils/__init__.py
fastapi_gateway_ultra/utils/body.py
fastapi_gateway_ultra/utils/form.py
fastapi_gateway_ultra/utils/headers.py
fastapi_gateway_ultra/utils/query.py
fastapi_gateway_ultra/utils/request.py
fastapi_gateway_ultra/utils/response.py
fastapi_gateway_ultra-0.1.1.dist-info/LICENSE
fastapi_gateway_ultra-0.1.1.dist-info/METADATA
fastapi_gateway_ultra-0.1.1.dist-info/WHEEL
fastapi_gateway_ultra-0.1.1.dist-info/RECORD
