Metadata-Version: 2.1
Name: fastapi-gateway-ultra
Version: 0.1.1
Summary: FastAPI gateway for microservices.
Home-page: https://github.com/xitowzys-ISZF/FastAPI-Gateway-Ultra
License: MIT
Keywords: python,fastapi,gateway,api,microservice,microservices,server side discovery
Author: dotX12
Requires-Python: >=3.7,<4.0
Classifier: License :: OSI Approved :: MIT License
Classifier: Programming Language :: Python :: 3
Classifier: Programming Language :: Python :: 3.7
Classifier: Programming Language :: Python :: 3.8
Classifier: Programming Language :: Python :: 3.9
Classifier: Programming Language :: Python :: 3.10
Classifier: Programming Language :: Python :: 3.11
Requires-Dist: aiohttp (>=3.7.4,<4.0.0)
Requires-Dist: ujson (>=5.5.0,<6.0.0)
Project-URL: Repository, https://github.com/xitowzys-ISZF/FastAPI-Gateway-Ultra
